pympanim/acts.py
pympanim/easing.py
pympanim/frame_gen.py
pympanim/image_stich.py
pympanim/utils.py
pympanim/worker.py
pympanim/zeromqqueue.py
pympanim-0.1.1.dist-info/LICENSE.txt
pympanim-0.1.1.dist-info/METADATA
pympanim-0.1.1.dist-info/WHEEL
pympanim-0.1.1.dist-info/top_level.txt
pympanim-0.1.1.dist-info/RECORD
