Metadata-Version: 2.1
Name: pympanim
Version: 0.1.1
Summary: Multiprocessing-friendly animations
Home-page: https://github.com/tjstretchalot/pympanim
Author: Timothy Moore
Author-email: mtimothy984@gmail.com
License: CC0
Keywords: pympanim animations video mp4
Classifier: Programming Language :: Python :: 3
Classifier: Programming Language :: Python :: 3.9
Classifier: Programming Language :: Python :: 3.10
Classifier: Programming Language :: Python :: 3.11
Classifier: Programming Language :: Python :: 3.12
Classifier: Programming Language :: Python :: 3.13
Classifier: License :: CC0 1.0 Universal (CC0 1.0) Public Domain Dedication
Classifier: Topic :: Utilities
Requires-Python: >=3.9
License-File: LICENSE.txt
Requires-Dist: pyzmq
Requires-Dist: pytypeutils
Requires-Dist: Pillow
Requires-Dist: psutil
